whatthepatch/__init__.py
whatthepatch/apply.py
whatthepatch/exceptions.py
whatthepatch/patch.py
whatthepatch/snippets.py
whatthepatch-1.0.2.dist-info/LICENSE
whatthepatch-1.0.2.dist-info/METADATA
whatthepatch-1.0.2.dist-info/WHEEL
whatthepatch-1.0.2.dist-info/top_level.txt
whatthepatch-1.0.2.dist-info/RECORD
